lepor/__init__.py
lepor/sentence_level.py
lepor-0.1.0.dist-info/METADATA
lepor-0.1.0.dist-info/WHEEL
lepor-0.1.0.dist-info/top_level.txt
lepor-0.1.0.dist-info/RECORD
