Metadata-Version: 2.1
Name: lepor
Version: 0.1.0
Summary: Python implementation of Machine Translation Evaluation Metric LEPOR.
Home-page: UNKNOWN
Author: Ikram Ul Haq
Author-email: ulhaqi12@gmail.com
License: MIT
Platform: UNKNOWN
Classifier: Intended Audience :: Developers
Classifier: License :: OSI Approved :: MIT License
Classifier: Programming Language :: Python
Classifier: Programming Language :: Python :: 3
Classifier: Programming Language :: Python :: 3.6
Classifier: Programming Language :: Python :: 3.7
Classifier: Programming Language :: Python :: 3.8
Classifier: Programming Language :: Python :: 3.9
Classifier: Operating System :: OS Independent
